LyaRT_Grid/__init__.py
LyaRT_Grid/DATA/List_of_DATA_files
LyaRT_Grid-0.0.9.dist-info/top_level.txt
LyaRT_Grid-0.0.9.dist-info/METADATA
LyaRT_Grid-0.0.9.dist-info/DESCRIPTION.rst
LyaRT_Grid-0.0.9.dist-info/metadata.json
LyaRT_Grid-0.0.9.dist-info/WHEEL
LyaRT_Grid-0.0.9.dist-info/RECORD
