Metadata-Version: 2.0
Name: LyaRT-Grid
Version: 0.0.9
Summary: A small example package
Home-page: https://github.com/pypa/example-project
Author: Example Author
Author-email: author@example.com
License: UNKNOWN
Platform: UNKNOWN
Classifier: Programming Language :: Python :: 3
Classifier: License :: OSI Approved :: MIT License
Classifier: Operating System :: OS Independent
Requires-Dist: LyaRT-Grid
